daydream/__init__.py
daydream/_version.py
daydream/basesdk.py
daydream/httpclient.py
daydream/public.py
daydream/py.typed
daydream/sdk.py
daydream/sdkconfiguration.py
daydream/streams.py
daydream/_hooks/__init__.py
daydream/_hooks/sdkhooks.py
daydream/_hooks/types.py
daydream/errors/__init__.py
daydream/errors/createstreamop.py
daydream/errors/daydreamdefaulterror.py
daydream/errors/daydreamerror.py
daydream/errors/deletestreamop.py
daydream/errors/getallstreamsop.py
daydream/errors/getstreambyidop.py
daydream/errors/no_response_error.py
daydream/errors/responsevalidationerror.py
daydream/errors/updatestreamop.py
daydream/models/__init__.py
daydream/models/createstreamop.py
daydream/models/deletestreamop.py
daydream/models/getallstreamsop.py
daydream/models/getstreambyidop.py
daydream/models/security.py
daydream/models/updatestreamop.py
daydream/types/__init__.py
daydream/types/basemodel.py
daydream/utils/__init__.py
daydream/utils/annotations.py
daydream/utils/datetimes.py
daydream/utils/enums.py
daydream/utils/eventstreaming.py
daydream/utils/forms.py
daydream/utils/headers.py
daydream/utils/logger.py
daydream/utils/metadata.py
daydream/utils/queryparams.py
daydream/utils/requestbodies.py
daydream/utils/retries.py
daydream/utils/security.py
daydream/utils/serializers.py
daydream/utils/unmarshal_json_response.py
daydream/utils/url.py
daydream/utils/values.py
daydream_sdk-0.1.0.dist-info/METADATA
daydream_sdk-0.1.0.dist-info/WHEEL
daydream_sdk-0.1.0.dist-info/top_level.txt
daydream_sdk-0.1.0.dist-info/RECORD
